.coveragerc
.gitignore
.travis.yml
LICENSE.md
LICENSE.mirumee.md
README.md
setup.py
tox.ini
tests/test_paypal.py
web_payments_paypal/__init__.py
web_payments_paypal/forms.py
web_payments_paypal.egg-info/PKG-INFO
web_payments_paypal.egg-info/SOURCES.txt
web_payments_paypal.egg-info/dependency_links.txt
web_payments_paypal.egg-info/requires.txt
web_payments_paypal.egg-info/top_level.txt
web_payments_paypal.egg-info/zip-safe